fern_fai_sdk/__init__.py
fern_fai_sdk/analytics/__init__.py
fern_fai_sdk/analytics/client.py
fern_fai_sdk/analytics/raw_client.py
fern_fai_sdk/chat/__init__.py
fern_fai_sdk/chat/client.py
fern_fai_sdk/chat/raw_client.py
fern_fai_sdk/client.py
fern_fai_sdk/code/__init__.py
fern_fai_sdk/code/client.py
fern_fai_sdk/code/raw_client.py
fern_fai_sdk/content_hash/__init__.py
fern_fai_sdk/content_hash/client.py
fern_fai_sdk/content_hash/raw_client.py
fern_fai_sdk/conversation/__init__.py
fern_fai_sdk/conversation/client.py
fern_fai_sdk/conversation/raw_client.py
fern_fai_sdk/core/__init__.py
fern_fai_sdk/core/api_error.py
fern_fai_sdk/core/client_wrapper.py
fern_fai_sdk/core/datetime_utils.py
fern_fai_sdk/core/file.py
fern_fai_sdk/core/force_multipart.py
fern_fai_sdk/core/http_client.py
fern_fai_sdk/core/http_response.py
fern_fai_sdk/core/http_sse/__init__.py
fern_fai_sdk/core/http_sse/_api.py
fern_fai_sdk/core/http_sse/_decoders.py
fern_fai_sdk/core/http_sse/_exceptions.py
fern_fai_sdk/core/http_sse/_models.py
fern_fai_sdk/core/jsonable_encoder.py
fern_fai_sdk/core/pydantic_utilities.py
fern_fai_sdk/core/query_encoder.py
fern_fai_sdk/core/remove_none_from_dict.py
fern_fai_sdk/core/request_options.py
fern_fai_sdk/core/serialization.py
fern_fai_sdk/discord/__init__.py
fern_fai_sdk/discord/client.py
fern_fai_sdk/discord/raw_client.py
fern_fai_sdk/document/__init__.py
fern_fai_sdk/document/client.py
fern_fai_sdk/document/raw_client.py
fern_fai_sdk/environment.py
fern_fai_sdk/errors/__init__.py
fern_fai_sdk/errors/unprocessable_entity_error.py
fern_fai_sdk/feedback/__init__.py
fern_fai_sdk/feedback/client.py
fern_fai_sdk/feedback/raw_client.py
fern_fai_sdk/guidance/__init__.py
fern_fai_sdk/guidance/client.py
fern_fai_sdk/guidance/raw_client.py
fern_fai_sdk/health/__init__.py
fern_fai_sdk/health/client.py
fern_fai_sdk/health/raw_client.py
fern_fai_sdk/index/__init__.py
fern_fai_sdk/index/client.py
fern_fai_sdk/index/raw_client.py
fern_fai_sdk/mcp/__init__.py
fern_fai_sdk-0.1.9.dist-info/METADATA
fern_fai_sdk-0.1.9.dist-info/WHEEL
fern_fai_sdk-0.1.9.dist-info/RECORD
